couchdb_storage/__init__.py
couchdb_storage/base_node.py
couchdb_storage/cli.py
couchdb_storage/couch_config.py
couchdb_storage/couch_db_py_couch.py
couchdb_storage/couch_db_storage.py
couchdb_storage/couch_tag_db.py
couchdb_storage/couch_utils.py
couchdb_storage/file_db.py
couchdb_storage/handle_tagged_files.py
couchdb_storage/laptop_node.py
couchdb_storage/net_utils.py
couchdb_storage/node_factory.py
couchdb_storage/tag_clipboard_files.py
couchdb_storage/tag_pwd.py
couchdb_storage/tag_utils.py
couchdb_storage/taggable.py
couchdb_storage/termux_node.py
couchdb_storage/windows_node.py
couchdb_storage-0.1.0.dist-info/AUTHORS.rst
couchdb_storage-0.1.0.dist-info/LICENSE
couchdb_storage-0.1.0.dist-info/METADATA
couchdb_storage-0.1.0.dist-info/WHEEL
couchdb_storage-0.1.0.dist-info/entry_points.txt
couchdb_storage-0.1.0.dist-info/top_level.txt
couchdb_storage-0.1.0.dist-info/RECORD
